NetCDFInterpolate.py
NetCDFInterpolate-0.1.dist-info/LICENSE
NetCDFInterpolate-0.1.dist-info/METADATA
NetCDFInterpolate-0.1.dist-info/WHEEL
NetCDFInterpolate-0.1.dist-info/top_level.txt
NetCDFInterpolate-0.1.dist-info/RECORD
